{
    "gb": {
        "center": [
            41.0,
            -111.95
        ],
        "forecasts": {},
        "huc_filter": [
            1601,
            160201,
            160202
        ],
        "huc_level": 4,
        "regions": {
            "Bear": {
                "anchor": [
                    0,
                    0
                ],
                "coords": [
                    41.6,
                    -112.75
                ],
                "huc-level": 4
            },
            "Great Salt Lake": {
                "anchor": [
                    0,
                    0
                ],
                "coords": [
                    40.77,
                    -112.5
                ],
                "huc-level": 4
            },
            "Jordan": {
                "anchor": [
                    0,
                    0
                ],
                "coords": [
                    40.7,
                    -111.98
                ],
                "huc-level": 8
            },
            "Lower Bear": {
                "anchor": [
                    0,
                    0
                ],
                "coords": [
                    41.6,
                    -112.31
                ],
                "huc-level": 6
            },
            "Provo": {
                "anchor": [
                    0,
                    0
                ],
                "coords": [
                    40.54,
                    -111.75
                ],
                "huc-level": 8
            },
            "Spanish Fork": {
                "anchor": [
                    0,
                    0
                ],
                "coords": [
                    40.1,
                    -111.58
                ],
                "huc-level": 8
            },
            "Upper Bear": {
                "anchor": [
                    0,
                    0
                ],
                "coords": [
                    41.66,
                    -111.21
                ],
                "huc-level": 6
            },
            "Weber": {
                "anchor": [
                    0,
                    0
                ],
                "coords": [
                    41.1,
                    -111.85
                ],
                "huc-level": 6
            }
        },
        "reservoirs": {
            "Causey": {
                "anchor": [
                    0,
                    0
                ],
                "anno": "",
                "cap": 7.07,
                "coords": [
                    41.29828,
                    -111.58591
                ],
                "id": 938,
                "pop_dir": "up",
                "region": "uc",
                "sdis": {
                    "elev": 1943,
                    "inflow": 1807,
                    "release": 1887,
                    "storage": 1736
                }
            },
            "Deer Creek": {
                "anchor": [
                    0,
                    0
                ],
                "anno": "",
                "cap": 150.161,
                "coords": [
                    40.40837,
                    -111.52908
                ],
                "id": 953,
                "pop_dir": "up",
                "region": "uc",
                "sdis": {
                    "elev": 1958,
                    "inflow": 1822,
                    "release": 1902,
                    "storage": 1751
                }
            },
            "East Canyon": {
                "anchor": [
                    28,
                    0
                ],
                "anno": "",
                "cap": 49.51,
                "coords": [
                    40.92027,
                    -111.60099
                ],
                "id": 940,
                "pop_dir": "up",
                "region": "uc",
                "sdis": {
                    "elev": 1945,
                    "inflow": 1809,
                    "release": 1889,
                    "storage": 1738
                }
            },
            "Echo": {
                "anchor": [
                    -28,
                    0
                ],
                "anno": "",
                "cap": 73.94,
                "coords": [
                    40.96412,
                    -111.43239
                ],
                "id": 941,
                "pop_dir": "up",
                "region": "uc",
                "sdis": {
                    "elev": 1946,
                    "inflow": 1810,
                    "release": 1890,
                    "storage": 1739
                }
            },
            "Hyrum": {
                "anchor": [
                    0,
                    0
                ],
                "anno": "",
                "cap": 14.734,
                "coords": [
                    41.62117,
                    -111.86099
                ],
                "id": 957,
                "pop_dir": "up",
                "region": "uc",
                "sdis": {
                    "elev": 1962,
                    "inflow": 1826,
                    "release": 1906,
                    "storage": 1755
                }
            },
            "Jordanelle": {
                "anchor": [
                    0,
                    0
                ],
                "anno": "",
                "cap": 311.0,
                "coords": [
                    40.59833,
                    -111.42304
                ],
                "id": 964,
                "pop_dir": "up",
                "region": "uc",
                "sdis": {
                    "elev": 1969,
                    "inflow": 1833,
                    "release": 1913,
                    "storage": 1762
                }
            },
            "Lost Creek": {
                "anchor": [
                    0,
                    0
                ],
                "anno": "",
                "cap": 22.501,
                "coords": [
                    41.18318,
                    -111.39905
                ],
                "id": 942,
                "pop_dir": "up",
                "region": "uc",
                "sdis": {
                    "elev": 1947,
                    "inflow": 1811,
                    "release": 1891,
                    "storage": 1740
                }
            },
            "Newton": {
                "anchor": [
                    0,
                    0
                ],
                "anno": "",
                "cap": 5.374,
                "coords": [
                    41.8998,
                    -111.97562
                ],
                "id": 959,
                "pop_dir": "up",
                "region": "uc",
                "sdis": {
                    "elev": 1964,
                    "inflow": 1828,
                    "release": 1908,
                    "storage": 1757
                }
            },
            "Rockport": {
                "anchor": [
                    0,
                    0
                ],
                "anno": "",
                "cap": 115.075,
                "coords": [
                    40.78944,
                    -111.40263
                ],
                "id": 947,
                "pop_dir": "up",
                "region": "uc",
                "sdis": {
                    "elev": 1952,
                    "inflow": 1816,
                    "release": 1896,
                    "storage": 1745
                }
            },
            "Willard Bay": {
                "anchor": [
                    0,
                    0
                ],
                "anno": "",
                "cap": 222.273,
                "coords": [
                    41.37738,
                    -112.08339
                ],
                "id": 925,
                "pop_dir": "up",
                "region": "uc",
                "sdis": {
                    "elev": 1932,
                    "inflow": 1796,
                    "release": 1876,
                    "storage": 1723
                }
            }
        },
        "zoom": 9
    },
    "gunn": {
        "center": [
            38.5,
            -107.5
        ],
        "forecasts": {},
        "huc_filter": 1402,
        "huc_level": 6,
        "regions": {
            "East-Taylor": {
                "anchor": [
                    0,
                    0
                ],
                "coords": [
                    39,
                    -106.9
                ],
                "huc-level": 8
            },
            "Gunnison": {
                "anchor": [
                    0,
                    0
                ],
                "coords": [
                    38.7,
                    -107.6
                ],
                "huc-level": 4
            },
            "Lower Gunnison": {
                "anchor": [
                    0,
                    0
                ],
                "coords": [
                    38.7,
                    -108.5
                ],
                "huc-level": 8
            },
            "North Fork Gunnison": {
                "anchor": [
                    0,
                    0
                ],
                "coords": [
                    39.04,
                    -107.74
                ],
                "huc-level": 8
            },
            "Pecos Headwaters": {
                "anchor": [
                    0,
                    0
                ],
                "coords": [
                    33,
                    -105
                ],
                "huc-level": 8
            },
            "Tomichi": {
                "anchor": [
                    0,
                    0
                ],
                "coords": [
                    38.5,
                    -106.7
                ],
                "huc-level": 8
            },
            "Uncompahgre": {
                "anchor": [
                    0,
                    0
                ],
                "coords": [
                    38.5,
                    -108.1
                ],
                "huc-level": 8
            }
        },
        "reservoirs": {
            "Blue Mesa": {
                "anchor": [
                    -40,
                    35
                ],
                "anno": "",
                "cap": 829.5,
                "coords": [
                    38.45305,
                    -107.33677
                ],
                "id": 913,
                "pop_dir": "up",
                "region": "uc",
                "sdis": {
                    "elev": 1923,
                    "inflow": 1787,
                    "release": 1867,
                    "storage": 1714
                }
            },
            "Crystal": {
                "anchor": [
                    -10,
                    10
                ],
                "anno": "",
                "cap": 17.536,
                "coords": [
                    38.51046,
                    -107.62374
                ],
                "id": 915,
                "pop_dir": "up",
                "region": "uc",
                "sdis": {
                    "elev": 1925,
                    "inflow": 1789,
                    "release": 1869,
                    "storage": 1716
                }
            },
            "Morrow Point": {
                "anchor": [
                    -10,
                    -25
                ],
                "anno": "",
                "cap": 117.025,
                "coords": [
                    38.45191,
                    -107.53791
                ],
                "id": 914,
                "pop_dir": "up",
                "region": "uc",
                "sdis": {
                    "elev": 1924,
                    "inflow": 1788,
                    "release": 1868,
                    "storage": 1715
                }
            },
            "Paonia": {
                "anchor": [
                    -10,
                    0
                ],
                "anno": "",
                "cap": 15.522,
                "coords": [
                    38.94919,
                    -107.34347
                ],
                "id": 945,
                "pop_dir": "up",
                "region": "uc",
                "sdis": {
                    "elev": 1950,
                    "inflow": 1814,
                    "release": 1894,
                    "storage": 1743
                }
            },
            "Ridgway": {
                "anchor": [
                    20,
                    0
                ],
                "anno": "",
                "cap": 82.98,
                "coords": [
                    38.23636,
                    -107.75914
                ],
                "id": 912,
                "pop_dir": "up",
                "region": "uc",
                "sdis": {
                    "elev": 1922,
                    "inflow": 1786,
                    "release": 1860,
                    "storage": 1713
                }
            },
            "Silver Jack": {
                "anchor": [
                    -20,
                    0
                ],
                "anno": "",
                "cap": 13.0,
                "coords": [
                    38.22692,
                    -107.54041
                ],
                "id": 939,
                "pop_dir": "up",
                "region": "uc",
                "sdis": {
                    "elev": 1944,
                    "inflow": 1808,
                    "release": 1888,
                    "storage": 1737
                }
            },
            "Taylor Park": {
                "anchor": [
                    0,
                    0
                ],
                "anno": "",
                "cap": 106.21,
                "coords": [
                    38.81844,
                    -106.60592
                ],
                "id": 948,
                "pop_dir": "up",
                "region": "uc",
                "sdis": {
                    "elev": 1953,
                    "inflow": 1817,
                    "release": 1897,
                    "storage": 1746
                }
            }
        },
        "zoom": 9
    },
    "pb": {
        "center": [
            39.03,
            -110.83
        ],
        "forecasts": {},
        "huc_filter": [
            14060007,
            14060009,
            14070002,
            14070003
        ],
        "huc_level": 6,
        "regions": {
            "Fremont": {
                "anchor": [
                    0,
                    0
                ],
                "coords": [
                    38.45,
                    -111.76
                ],
                "huc-level": 8
            },
            "Lower Green": {
                "anchor": [
                    0,
                    0
                ],
                "coords": [
                    39.67,
                    -111.53
                ],
                "huc-level": 6
            },
            "Muddy": {
                "anchor": [
                    0,
                    0
                ],
                "coords": [
                    38.75,
                    -111.2
                ],
                "huc-level": 8
            },
            "Price": {
                "anchor": [
                    0,
                    0
                ],
                "coords": [
                    39.57,
                    -110.85
                ],
                "huc-level": 8
            },
            "San Rafael": {
                "anchor": [
                    0,
                    0
                ],
                "coords": [
                    39.06,
                    -110.9
                ],
                "huc-level": 8
            },
            "Upper Colorado-Dirty Devil": {
                "anchor": [
                    0,
                    0
                ],
                "coords": [
                    38.72,
                    -111.86
                ],
                "huc-level": 6
            }
        },
        "reservoirs": {
            "Huntington North": {
                "anchor": [
                    0,
                    10
                ],
                "anno": "",
                "cap": 1105.91,
                "coords": [
                    39.38458,
                    -111.09082
                ],
                "id": 956,
                "pop_dir": "up",
                "region": "uc",
                "sdis": {
                    "elev": 1961,
                    "inflow": 1825,
                    "release": 1905,
                    "storage": 1754
                }
            },
            "Joes Valley": {
                "anchor": [
                    0,
                    0
                ],
                "anno": "",
                "cap": 61.59,
                "coords": [
                    39.2901,
                    -111.27888
                ],
                "id": 932,
                "pop_dir": "up",
                "region": "uc",
                "sdis": {
                    "elev": 1937,
                    "inflow": 1801,
                    "release": 1881,
                    "storage": 1730
                }
            },
            "Scofield": {
                "anchor": [
                    0,
                    -10
                ],
                "anno": "",
                "cap": 65.8,
                "coords": [
                    39.77656,
                    -111.05074
                ],
                "id": 931,
                "pop_dir": "up",
                "region": "uc",
                "sdis": {
                    "elev": 1936,
                    "inflow": 1800,
                    "release": 1880,
                    "storage": 1729
                }
            }
        },
        "zoom": 9
    },
    "rg": {
        "center": [
            35.3,
            -106
        ],
        "forecasts": {},
        "huc_filter": 13,
        "huc_level": 2,
        "regions": {
            "Rio Grande": {
                "anchor": [
                    0,
                    0
                ],
                "coords": [
                    35.5,
                    -107
                ],
                "huc-level": 2
            },
            "Rio Grande Headwaters": {
                "anchor": [
                    0,
                    0
                ],
                "coords": [
                    38.25,
                    -106.65
                ],
                "huc-level": 6
            },
            "Rio Grande-Elephant Butte": {
                "anchor": [
                    0,
                    0
                ],
                "coords": [
                    34.7,
                    -108.2
                ],
                "huc-level": 6
            },
            "Upper Pecos": {
                "anchor": [
                    0,
                    0
                ],
                "coords": [
                    33.6,
                    -105.3
                ],
                "huc-level": 6
            },
            "Upper Rio Grande": {
                "anchor": [
                    0,
                    0
                ],
                "coords": [
                    36.9,
                    -106.85
                ],
                "huc-level": 6
            },
            "Upper San Juan": {
                "anchor": [
                    0,
                    0
                ],
                "coords": [
                    37,
                    -108.65
                ],
                "huc-level": 8
            }
        },
        "reservoirs": {
            "Elephant Butte": {
                "anchor": [
                    0,
                    0
                ],
                "anno": "",
                "cap": 2010.9,
                "coords": [
                    33.15,
                    -107.2
                ],
                "id": 1119,
                "pop_dir": "left",
                "region": "uc",
                "sdis": {
                    "elev": 2685,
                    "inflow": 2686,
                    "release": 2688,
                    "storage": 2684
                }
            }
        },
        "zoom": 7
    },
    "sj": {
        "center": [
            37,
            -108.1
        ],
        "forecasts": {},
        "huc_filter": 1408,
        "huc_level": 4,
        "regions": {
            "Animas": {
                "anchor": [
                    0,
                    0
                ],
                "coords": [
                    37.65,
                    -107.8
                ],
                "huc-level": 8
            },
            "Chaco": {
                "anchor": [
                    0,
                    0
                ],
                "coords": [
                    36.45,
                    -108.84
                ],
                "huc-level": 8
            },
            "Chinle": {
                "anchor": [
                    0,
                    0
                ],
                "coords": [
                    36.8,
                    -109.8
                ],
                "huc-level": 8
            },
            "Mancos": {
                "anchor": [
                    0,
                    0
                ],
                "coords": [
                    37.2,
                    -108.7
                ],
                "huc-level": 8
            },
            "Middle San Juan": {
                "anchor": [
                    0,
                    0
                ],
                "coords": [
                    36.9,
                    -109
                ],
                "huc-level": 8
            },
            "Montezuma": {
                "anchor": [
                    0,
                    0
                ],
                "coords": [
                    37.7,
                    -109.28
                ],
                "huc-level": 8
            },
            "Piedra": {
                "anchor": [
                    0,
                    0
                ],
                "coords": [
                    37.53,
                    -107.34
                ],
                "huc-level": 8
            },
            "San Juan": {
                "anchor": [
                    0,
                    0
                ],
                "coords": [
                    37,
                    -108.26
                ],
                "huc-level": 4
            },
            "Upper San Juan": {
                "anchor": [
                    0,
                    0
                ],
                "coords": [
                    37,
                    -107
                ],
                "huc-level": 8
            }
        },
        "reservoirs": {
            "Jackson": {
                "anchor": [
                    0,
                    0
                ],
                "anno": "",
                "cap": 115.075,
                "coords": [
                    37.40186,
                    -108.27342
                ],
                "id": 935,
                "pop_dir": "up",
                "region": "uc",
                "sdis": {
                    "elev": 1940,
                    "inflow": 1804,
                    "release": 1884,
                    "storage": 1733
                }
            },
            "Lemon": {
                "anchor": [
                    0,
                    0
                ],
                "anno": "",
                "cap": 39.792,
                "coords": [
                    37.39538,
                    -107.66269
                ],
                "id": 934,
                "pop_dir": "up",
                "region": "uc",
                "sdis": {
                    "elev": 1939,
                    "inflow": 1803,
                    "release": 1883,
                    "storage": 1732
                }
            },
            "McPhee": {
                "anchor": [
                    0,
                    0
                ],
                "anno": "",
                "cap": 381.0,
                "coords": [
                    37.57588,
                    -108.57307
                ],
                "id": 958,
                "pop_dir": "up",
                "region": "uc",
                "sdis": {
                    "elev": 1963,
                    "inflow": 1827,
                    "release": 1907,
                    "storage": 1756
                }
            },
            "Navajo": {
                "anchor": [
                    0,
                    0
                ],
                "anno": "",
                "cap": 1701.3,
                "coords": [
                    36.80063,
                    -107.61203
                ],
                "id": 920,
                "pop_dir": "up",
                "region": "uc",
                "sdis": {
                    "elev": 1929,
                    "inflow": 1793,
                    "release": 1873,
                    "storage": 1720
                }
            },
            "Nighthorse": {
                "anchor": [
                    0,
                    0
                ],
                "anno": "",
                "cap": 115.075,
                "coords": [
                    37.22392,
                    -107.91694
                ],
                "id": 3083,
                "pop_dir": "up",
                "region": "uc",
                "sdis": {
                    "elev": 14621,
                    "inflow": 14617,
                    "release": 14620,
                    "storage": 14623
                }
            },
            "Vallecito": {
                "anchor": [
                    -85,
                    -40
                ],
                "anno": "",
                "cap": 125.442,
                "coords": [
                    37.37834,
                    -107.57486
                ],
                "id": 933,
                "pop_dir": "up",
                "region": "uc",
                "sdis": {
                    "elev": 1938,
                    "inflow": 1802,
                    "release": 1882,
                    "storage": 1731
                }
            }
        },
        "zoom": 9
    },
    "ub": {
        "center": [
            40.3,
            -110.15
        ],
        "forecasts": {},
        "huc_filter": [
            14060003,
            14060004,
            14060005,
            14060010
        ],
        "huc_level": 6,
        "regions": {
            "Duchesne": {
                "anchor": [
                    0,
                    0
                ],
                "coords": [
                    40.42,
                    -110.65
                ],
                "huc-level": 8
            },
            "Lower Green": {
                "anchor": [
                    0,
                    0
                ],
                "coords": [
                    40.4,
                    -110.23
                ],
                "huc-level": 6
            },
            "Lower Green-Desolation Canyon": {
                "anchor": [
                    0,
                    0
                ],
                "coords": [
                    40.1,
                    -110.1
                ],
                "huc-level": 8
            },
            "Lower Green-Diamond": {
                "anchor": [
                    0,
                    0
                ],
                "coords": [
                    40.3,
                    -109.5
                ],
                "huc-level": 8
            },
            "Strawberry": {
                "anchor": [
                    0,
                    0
                ],
                "coords": [
                    40.2,
                    -110.75
                ],
                "huc-level": 8
            }
        },
        "reservoirs": {
            "Currant Creek": {
                "anchor": [
                    0,
                    0
                ],
                "anno": "",
                "cap": 15.464,
                "coords": [
                    40.33841,
                    -111.05821
                ],
                "id": 952,
                "pop_dir": "up",
                "region": "uc",
                "sdis": {
                    "elev": 1957,
                    "inflow": 1821,
                    "release": 1901,
                    "storage": 1750
                }
            },
            "Moon Lake": {
                "anchor": [
                    0,
                    0
                ],
                "anno": "",
                "cap": 37.848,
                "coords": [
                    40.57445,
                    -110.50665
                ],
                "id": 930,
                "pop_dir": "up",
                "region": "uc",
                "sdis": {
                    "elev": 1935,
                    "inflow": 1799,
                    "release": 1879,
                    "storage": 1728
                }
            },
            "Red Fleet": {
                "anchor": [
                    0,
                    0
                ],
                "anno": "",
                "cap": 25.7,
                "coords": [
                    40.57543,
                    -109.42052
                ],
                "id": 960,
                "pop_dir": "up",
                "region": "uc",
                "sdis": {
                    "elev": 1965,
                    "inflow": 1829,
                    "release": 1909,
                    "storage": 1758
                }
            },
            "Soldier Creek": {
                "anchor": [
                    0,
                    0
                ],
                "anno": "",
                "cap": 1105.91,
                "coords": [
                    40.13564,
                    -111.02659
                ],
                "id": 962,
                "pop_dir": "up",
                "region": "uc",
                "sdis": {
                    "elev": 1967,
                    "inflow": 1831,
                    "release": 1911,
                    "storage": 1760
                }
            },
            "Starvation": {
                "anchor": [
                    0,
                    0
                ],
                "anno": "",
                "cap": 162.279,
                "coords": [
                    40.19324,
                    -110.44722
                ],
                "id": 928,
                "pop_dir": "up",
                "region": "uc",
                "sdis": {
                    "elev": 1934,
                    "inflow": 1798,
                    "release": 1878,
                    "storage": 1726
                }
            },
            "Steinaker": {
                "anchor": [
                    0,
                    0
                ],
                "anno": "",
                "cap": 36.148,
                "coords": [
                    40.51456,
                    -109.53275
                ],
                "id": 927,
                "pop_dir": "up",
                "region": "uc",
                "sdis": {
                    "elev": 1933,
                    "inflow": 1797,
                    "release": 1877,
                    "storage": 1725
                }
            },
            "Upper Stillwater": {
                "anchor": [
                    0,
                    0
                ],
                "anno": "",
                "cap": 31.382,
                "coords": [
                    40.56565,
                    -110.70044
                ],
                "id": 963,
                "pop_dir": "up",
                "region": "uc",
                "sdis": {
                    "elev": 1968,
                    "inflow": 1832,
                    "release": 1912,
                    "storage": 1761
                }
            }
        },
        "zoom": 10
    },
    "uc": {
        "center": [
            39.3,
            -109.1
        ],
        "forecasts": {},
        "huc_filter": 14,
        "huc_level": 2,
        "regions": {
            "Colorado Headwaters": {
                "anchor": [
                    0,
                    0
                ],
                "coords": [
                    40,
                    -107.1
                ],
                "huc-level": 6
            },
            "Gunnison": {
                "anchor": [
                    0,
                    0
                ],
                "coords": [
                    39.0,
                    -108.3
                ],
                "huc-level": 6
            },
            "Lower Green": {
                "anchor": [
                    0,
                    0
                ],
                "coords": [
                    40.5,
                    -110.8
                ],
                "huc-level": 6
            },
            "Lower San Juan": {
                "anchor": [
                    0,
                    0
                ],
                "coords": [
                    37.7,
                    -110.2
                ],
                "huc-level": 6
            },
            "Upper Colorado": {
                "anchor": [
                    0,
                    0
                ],
                "coords": [
                    39.8,
                    -110.7
                ],
                "huc-level": 2
            },
            "Upper Colorado-Dirty Devil": {
                "anchor": [
                    0,
                    0
                ],
                "coords": [
                    38.2,
                    -112.25
                ],
                "huc-level": 6
            },
            "Upper Colorado-Dolores": {
                "anchor": [
                    0,
                    0
                ],
                "coords": [
                    37.7,
                    -108.2
                ],
                "huc-level": 6
            },
            "Upper Green": {
                "anchor": [
                    0,
                    0
                ],
                "coords": [
                    42.9,
                    -110.5
                ],
                "huc-level": 6
            },
            "Upper San Juan": {
                "anchor": [
                    0,
                    0
                ],
                "coords": [
                    36.3,
                    -108.5
                ],
                "huc-level": 6
            },
            "White-Yampa": {
                "anchor": [
                    0,
                    0
                ],
                "coords": [
                    40.9,
                    -107.9
                ],
                "huc-level": 6
            }
        },
        "reservoirs": {
            "Blue Mesa": {
                "anchor": [
                    -110,
                    25
                ],
                "anno": "",
                "cap": 829.5,
                "coords": [
                    38.453,
                    -107.337
                ],
                "id": 913,
                "pop_dir": "right",
                "region": "uc",
                "sdis": {
                    "elev": 1923,
                    "inflow": 1787,
                    "release": 1867,
                    "storage": 1714
                }
            },
            "Crystal": {
                "anchor": [
                    105,
                    -25
                ],
                "anno": "",
                "cap": 17.536,
                "coords": [
                    38.51,
                    -107.624
                ],
                "id": 915,
                "pop_dir": "left",
                "region": "uc",
                "sdis": {
                    "elev": 1925,
                    "inflow": 1844,
                    "release": 1869,
                    "storage": 1716
                }
            },
            "Flaming Gorge": {
                "anchor": [
                    0,
                    0
                ],
                "anno": "",
                "cap": 3749,
                "coords": [
                    41.0934,
                    -109.5406
                ],
                "id": 917,
                "pop_dir": "right",
                "region": "uc",
                "sdis": {
                    "elev": 1927,
                    "inflow": 1791,
                    "release": 1871,
                    "storage": 1718
                }
            },
            "Fontenelle": {
                "anchor": [
                    0,
                    0
                ],
                "anno": "",
                "cap": 344.8,
                "coords": [
                    42.026,
                    -110.068
                ],
                "id": 916,
                "pop_dir": "left",
                "region": "uc",
                "sdis": {
                    "elev": 1926,
                    "inflow": 1790,
                    "release": 1870,
                    "storage": 1717
                }
            },
            "Lake Powell": {
                "anchor": [
                    0,
                    0
                ],
                "anno": "",
                "cap": 24322,
                "coords": [
                    37.0688,
                    -111.2439
                ],
                "id": 919,
                "pop_dir": "up",
                "region": "uc",
                "sdis": {
                    "elev": 1928,
                    "inflow": 1792,
                    "release": 1872,
                    "storage": 1719
                }
            },
            "Morrow Point": {
                "anchor": [
                    0,
                    0
                ],
                "anno": "",
                "cap": 117.25,
                "coords": [
                    38.452,
                    -107.538
                ],
                "id": 914,
                "pop_dir": "up",
                "region": "uc",
                "sdis": {
                    "elev": 1924,
                    "inflow": 1843,
                    "release": 1868,
                    "storage": 1715
                }
            },
            "Navajo": {
                "anchor": [
                    0,
                    0
                ],
                "anno": "",
                "cap": 1696,
                "coords": [
                    36.801,
                    -107.612
                ],
                "id": 920,
                "pop_dir": "up",
                "region": "uc",
                "sdis": {
                    "elev": 1929,
                    "inflow": 1793,
                    "release": 1873,
                    "storage": 1720
                }
            }
        },
        "zoom": 7
    }
}